README.md
setup.py
pycybersource/__init__.py
pycybersource/base.py
pycybersource/config.py
pycybersource/response.py
pycybersource.egg-info/PKG-INFO
pycybersource.egg-info/SOURCES.txt
pycybersource.egg-info/dependency_links.txt
pycybersource.egg-info/requires.txt
pycybersource.egg-info/top_level.txt