Metadata-Version: 1.1
Name: pycybersource
Version: 0.1.2a0
Summary: A light wrapper for Cybersource SOAP Toolkit API
Home-page: UNKNOWN
Author: Eric Bartels
Author-email: ebartels@gmail.com
License: BSD
Keywords: cybersource payment soap zeep api wrapper
Platform: Platform Independent
Classifier: Development Status :: 3 - Alpha
Classifier: Intended Audience :: Developers
Classifier: License :: OSI Approved :: BSD License
Classifier: Natural Language :: English
Classifier: Operating System :: OS Independent
Classifier: Programming Language :: Python :: 3.6
Classifier: Topic :: Software Development :: Libraries :: Python Modules
Requires: zeep
